flirt/__init__.py
flirt/flirt.pypy311-pp73-x86_64-linux-gnu.so
python_flirt-0.9.10.dist-info/METADATA
python_flirt-0.9.10.dist-info/WHEEL
python_flirt-0.9.10.dist-info/licenses/LICENSE.txt
python_flirt-0.9.10.dist-info/RECORD
