Metadata-Version: 2.4
Name: python-flirt
Version: 0.9.10
Classifier: License :: OSI Approved :: Apache Software License
Classifier: Natural Language :: English
Classifier: Operating System :: OS Independent
Classifier: Topic :: Security
Classifier: Topic :: Software Development :: Disassemblers
Classifier: Development Status :: 3 - Alpha
Classifier: Programming Language :: Rust
Requires-Dist: maturin>=1.7.4 ; extra == 'dev'
Requires-Dist: pytest>=7.1.3 ; extra == 'dev'
Requires-Dist: pytest-sugar>=0.9.4 ; extra == 'dev'
Requires-Dist: pytest-instafail>=0.4.2 ; extra == 'dev'
Requires-Dist: pytest-cov>=4.0.0 ; extra == 'dev'
Requires-Dist: pycodestyle>=2.9.1 ; extra == 'dev'
Requires-Dist: black>=22.10.0 ; extra == 'dev'
Requires-Dist: isort>=5.10.1 ; extra == 'dev'
Requires-Dist: mypy>=0.982 ; extra == 'dev'
Provides-Extra: dev
License-File: LICENSE.txt
Summary: A Python library for parsing, compiling, and matching Fast Library Identification and Recognition Technology (FLIRT) signatures.
Keywords: flirt
Home-Page: https://github.com/williballenthin/lancelot/tree/master/pyflirt
Author-email: Willi Ballenthin <william.ballenthin@mandiant.com>
Maintainer-email: Willi Ballenthin <william.ballenthin@mandiant.com>
Requires-Python: >=3.10
Project-URL: repository, https://github.com/williballenthin/lancelot/tree/master/pyflirt
